Metadata-Version: 2.1
Name: panphlan
Version: 3.0
Summary: PanPhlAn is a strain-level metagenomic profiling tool for identifying the gene composition and *in-vivo* transcriptional activity of individual strains in metagenomic samples. PanPhlAn’s ability for strain-tracking and functional analysis of unknown pathogens makes it an efficient tool for culture-free infectious outbreak epidemiology and microbial population studies.
Home-page: http://github.com/SegataLab/panphlan/
Author: Leonard Dubois
Author-email: leonard.dubois@unitn.it
License: UNKNOWN
Platform: UNKNOWN
